django_wsx-0.1.1.dist-info/licenses/LICENSE
wsx/__init__.py
wsx/actions.py
wsx/apps.py
wsx/auth.py
wsx/auth_request.py
wsx/exceptions.py
wsx/groups.py
wsx/middleware.py
wsx/orm.py
wsx/permissions.py
wsx/py.typed
wsx/redis_throttles.py
wsx/request.py
wsx/response.py
wsx/router.py
wsx/routes.py
wsx/schema.py
wsx/serializers.py
wsx/settings.py
wsx/throttles.py
wsx/utils.py
wsx/views.py
wsx/migrations/__init__.py
django_wsx-0.1.1.dist-info/METADATA
django_wsx-0.1.1.dist-info/WHEEL
django_wsx-0.1.1.dist-info/top_level.txt
django_wsx-0.1.1.dist-info/RECORD
