Metadata-Version: 2.4
Name: django-wsx
Version: 0.1.1
Summary: DRF-style WebSockets for Django/Channels (Actions, serializers, permissions, throttles)
Author: YOUR NAME
License:                                  Apache License
Project-URL: Homepage, https://github.com/YOUR_GITHUB/django-wsx
Project-URL: Repository, https://github.com/YOUR_GITHUB/django-wsx
Project-URL: Issues, https://github.com/YOUR_GITHUB/django-wsx/issues
Project-URL: Changelog, https://github.com/YOUR_GITHUB/django-wsx/blob/main/CHANGELOG.md
Keywords: django,websocket,channels,drf,realtime,jwt,redis
Classifier: Development Status :: 3 - Alpha
Classifier: Framework :: Django
Classifier: Framework :: Django :: 4
Classifier: Programming Language :: Python :: 3
Classifier: Programming Language :: Python :: 3 :: Only
Classifier: License :: OSI Approved :: MIT License
Classifier: Intended Audience :: Developers
Classifier: Topic :: Internet :: WWW/HTTP
Classifier: Topic :: Software Development :: Libraries :: Application Frameworks
Requires-Python: >=3.10
License-File: LICENSE
Requires-Dist: Django>=4.2
Requires-Dist: channels>=4.0
Requires-Dist: asgiref>=3.7
Provides-Extra: redis
Requires-Dist: channels-redis>=4.2; extra == "redis"
Requires-Dist: django-redis>=5.4; extra == "redis"
Provides-Extra: direct-redis
Requires-Dist: redis>=5.0; extra == "direct-redis"
Provides-Extra: dev
Requires-Dist: pytest>=7.0; extra == "dev"
Requires-Dist: pytest-asyncio>=0.23; extra == "dev"
Requires-Dist: ruff>=0.5; extra == "dev"
Requires-Dist: mypy>=1.8; extra == "dev"
Requires-Dist: build>=1.0; extra == "dev"
Requires-Dist: twine>=4.0; extra == "dev"
Dynamic: license-file
